{
  "name": "Jhon Mcneil Magtibay",
  "title": "Full Stack Developer",
  "avatar": "images/ID_pic.png",
  "about": "Hi! I'm Mcneil. \n \nI'm a full-stack developer who specializes in backend development, with a strong focus on building efficient, scalable, and secure server-side applications. I love tackling complex problems and designing systems that run smoothly behind the scenes while ensuring a seamless experience on the front end. \n\nWhen I’m not coding, you’ll probably find me immersed in survival and puzzle games — I enjoy the challenge of strategic thinking and problem-solving, whether it’s surviving in a digital wilderness or cracking intricate puzzles.",
  "education": [
    {
      "degree": "Bachelor of Science in Information Technology major in Business Analiytics",
      "institution": "Batangas State University The National Engineering School - Mabini Campus",
      "year": "2023 - Present"
    },
    {
      "degree": "Senior High School - ICT Strand",
      "institution": "Anselmo A. Sandoval Memorial National High School",
      "year": "2021 - 2023",
      "details": "Graduated with High Honors"
    }
  ],
  "chips": ["Web Development", "Backend Development", "Frontend Development"],
  "skills": ["Angular", "Nodejs", "Java", "Responsive UI", "JavaScript", "HTML", "CSS", "MySQL", "Python"],
  "projects": [
    { 
      "title": "VaultX ATM CLI Process", 
      "description": "A command-line interface for ATM transactions.",
      "languages": ["Java", "MySQL"],
      "repository": "https://github.com/Mcneil-official/ATM_process",
      "image": "images/projects/vaultx.png"
    },
    { 
      "title": "Tourism Website", 
      "description": "Beautiful tourism website showcasing destinations and packages.",
      "languages": ["HTML", "CSS", "JavaScript", "Bootstrap"],
      "repository": "https://github.com/Mcneil-official/Tourism",
      "deployment": "https://tourism-swart-zeta.vercel.app/",
      "image": "images/projects/tourism.png"
    },
    { 
      "title": "Pathpickr", 
      "description": "A track recommending website for students that helps them find suitable study paths.",
      "languages": ["HTML", "CSS", "Java", "JavaScript"],
      "repository": "https://github.com/Mcneil-official/PathPickr",
      "image": "images/projects/pathpickr.png"
    },
    { 
      "title": "Login API with OAuth2", 
      "description": "A RESTful API for user authentication and management.",
      "languages": ["JavaScript", "Node.js", "Express", "OAuth2"],
      "repository": "https://github.com/Mcneil-official/login"
    },
    {
      "title": "Signup API with OAuth2",
      "description": "A RESTful API for user registration.",
      "languages": ["JavaScript", "Node.js", "Express", "OAuth2"],
      "repository": "https://github.com/Mcneil-official/AST2008-Implement-User-Signup-API-NodeJS-SQLite-"
    },
    { 
      "title": "CRUD System", 
      "description": "A simple CRUD application for managing records.",
      "languages": ["Angular", "TypeScript", "JSON Server"],
      "repository": "https://github.com/Mcneil-official/crud-app",
      "image": "images/projects/crudsystem.png"
    },
        { 
      "title": "CRUD Student Management System", 
      "description": "A web-based application for managing student records.",
      "languages": ["Angular", "TypeScript", "JSON Server"],
      "repository": "https://github.com/Mcneil-official/student_management_system",
      "image": "images/projects/studentmanagement.png"
    },
    { 
      "title": "Oh Crepe!: E-commerce Website", 
      "description": "An e-commerce website for a fictional crepe shop.",
      "languages": ["Angular", "TypeScript", "CSS", "Node.js", "JavaScript"],
      "repository": "hhttps://github.com/Mcneil-official/Oh-crepe-",
      "deployment": "https://oh-crepe-seven.vercel.app/",
      "image": "images/projects/ohcrepe.png"
    },
    {
      "title": "Simple Sign Language Detection",
      "description": "A project that utilizes machine learning to detect and interpret sign language gestures.",
      "languages": ["Python"],
      "repository": "https://github.com/Mcneil-official/Simple-Sign-Language-Detection",
      "image" : "images/projects/signlanguage.png"
    }
  ],
  "notable achievements": [
    {
      "title": "Learning Express Program 2025",
      "description": "Participated in LeX Program2025: Global to Local Community Engagement, hosted by BatState-U TNEU, in partnership with Singapore Polytechnic. ",
      "year": "2025"
    },
    {
      "title": "CICS Governor Mabini in Supreme Student Council",
      "description": "Elected as the CICS Governor Mabini in Supreme Student Council for the 2025-2026 academic year",
      "year": "2025-2026"
    },
    {
      "title": "Vice President for External Affairs in CICS Mabini Student Council",
      "description": "Elected as the Vice President for External Affairs of CICS Mabini Student Council for the 2025-2026 academic year",
      "year": "2025-2026"
    },
    {
      "title": "President in CICS Mabini Student Council",
      "description": "Elected as the President of CICS Mabini Student Council for the 2024-2025 academic year",
      "year": "2024-2025"
    },
    {
      "title": "1st Year Representative in CICS Mabini Student Council",
      "description": "Assigned as the 1st year representative in CICS Mabini Student Council for the 2023-2024 academic year",
      "year": "2023-2024"
    },
    {
      "title": "Computer System Servicing NC II",
      "description": "Completed the National Certificate II for Computer Systems Servicing under TESDA",
      "year": "2023"
    }
  ],
  "school_projects": [
    {
    "title": "NutriBlend Lookers Report",
    "description": "A Lookers Studio report analyzing the sales and performance of NutriBlend products.",
    "link": "https://lookerstudio.google.com/s/nEu10wluDOc"
    }
  ],
  "contact": {
    "email": "jhonmcneilmagtibay5002@gmail.com",
    "linkedin": "linkedin.com/in/jhon-mcneil-magtibay",
    "github": "github.com/JhonMcFrost",
    "facebook": "facebook.com/jhonmcneil.magtibay.7",
    "instagram": "instagram.com/jhon_mc.neil"
  }
}
